pyevacalor/__init__.py
pyevacalor-0.0.10.dist-info/LICENSE
pyevacalor-0.0.10.dist-info/METADATA
pyevacalor-0.0.10.dist-info/WHEEL
pyevacalor-0.0.10.dist-info/top_level.txt
pyevacalor-0.0.10.dist-info/RECORD
