Metadata-Version: 2.1
Name: pyevacalor
Version: 0.0.10
Summary: pyevacalor provides controlling Eva Calor heating devices connected via the IOT Agua platform of Micronova
Home-page: https://github.com/fredericvl/pyevacalor
Author: Frederic Van Linthoudt
Author-email: frederic.van.linthoudt@gmail.com
License: UNKNOWN
Platform: UNKNOWN
Classifier: Programming Language :: Python :: 3
Classifier: License :: OSI Approved :: Apache Software License
Classifier: Operating System :: OS Independent
Requires-Dist: PyJWT (==1.7.1)
Requires-Dist: requests (==2.25.1)
